Metadata-Version: 1.0
Name: bark-client
Version: 0.0.2
Summary: Bark client api
Home-page: https://github.com/pushyzheng
Author: Pushy
Author-email: 1437876073@qq.com
License: UNKNOWN
Platform: UNKNOWN
